[
    {
        "id": 2377206032848,
        "title": "Евгений Онегин",
        "author": "Александр Сергеевич Пушкин",
        "year": 1822,
        "status": "в наличии"
    },
    {
        "id": 2377206032976,
        "title": "Преступление и наказание",
        "author": "Фёдор Михайлович Достоевский",
        "year": 1878,
        "status": "в наличии"
    },
    {
        "id": 2377206033232,
        "title": "Герой нашего времени",
        "author": "Михаил Юрьевич Лермонтов",
        "year": 1835,
        "status": "в наличии"
    }
]